fourequalsten_hint/__init__.py
fourequalsten_hint/example.py
fourequalsten_hint/feth.py
fourequalsten_hint-1.0.4.dist-info/METADATA
fourequalsten_hint-1.0.4.dist-info/WHEEL
fourequalsten_hint-1.0.4.dist-info/licenses/LICENSE
fourequalsten_hint-1.0.4.dist-info/RECORD
