Metadata-Version: 2.1
Name: fourequalsten_hint
Version: 1.0.4
Summary: 4=10's Solution Generator - by Cheewy
Project-URL: Github Depository, https://github.com/CheewyOFF/fourequalsten_hint
Author-email: Cheewy <cheewy.perso@gmail.com>
License: Copyright (c) 2022 Cheewy
License-File: LICENSE
Classifier: License :: OSI Approved :: MIT License
Classifier: Operating System :: OS Independent
Classifier: Programming Language :: Python :: 3
Requires-Python: >=3.7
